{
  "next": "/v1/me/recent/played/tracks?offset=30",
  "data": [
    {
      "id": "1626233053",
      "type": "songs",
      "href": "/v1/catalog/us/songs/1626233053",
      "attributes": {
        "albumName": "Op.22 Y-Waltz : in Major - EP",
        "genreNames": [
          "K-Pop",
          "Music",
          "Pop"
        ],
        "trackNumber": 2,
        "releaseDate": "2022-06-02",
        "durationInMillis": 199067,
        "isrc": "KRA492200507",
        "artwork": {
          "width": 1400,
          "height": 1400,
          "url": "https://is1-ssl.mzstatic.com/image/thumb/Music112/v4/02/ab/38/02ab38b1-0048-35fa-058d-70aab34a408e/888272100082_Cover.jpg/{w}x{h}bb.jpg",
          "bgColor": "f9f8f4",
          "textColor1": "060605",
          "textColor2": "1e1a17",
          "textColor3": "363635",
          "textColor4": "494643"
        },
        "composerName": "The Proof, Moa \u201cCazzi Opeia\u201d Carlebecker, Albin Nordqvist, Maria Marcus, Danke & \uc870\uc724\uacbd",
        "playParams": {
          "id": "1626233053",
          "kind": "song"
        },
        "url": "https://music.apple.com/us/album/love-shhh/1626232826?i=1626233053",
        "discNumber": 1,
        "isAppleDigitalMaster": false,
        "hasLyrics": true,
        "name": "Love Shhh!",
        "previews": [
          {
            "url": "https://audio-ssl.itunes.apple.com/itunes-assets/AudioPreview122/v4/cb/12/66/cb1266e1-ee4b-9a08-2059-748a339d7952/mzaf_17031982910428537100.plus.aac.p.m4a"
          }
        ],
        "artistName": "JO YURI"
      }
    },
    {
      "id": "1649325667",
      "type": "songs",
      "href": "/v1/catalog/us/songs/1649325667",
      "attributes": {
        "albumName": "Gloria",
        "genreNames": [
          "Pop",
          "Music"
        ],
        "trackNumber": 11,
        "releaseDate": "2023-01-27",
        "durationInMillis": 229605,
        "isrc": "GBUM72205420",
        "artwork": {
          "width": 3000,
          "height": 3000,
          "url": "https://is5-ssl.mzstatic.com/image/thumb/Music122/v4/0d/97/a6/0d97a649-760f-522c-269d-9d710dc372ba/22UM1IM07174.rgb.jpg/{w}x{h}bb.jpg",
          "bgColor": "36311d",
          "textColor1": "e4c29d",
          "textColor2": "e0a581",
          "textColor3": "c1a583",
          "textColor4": "be8e6d"
        },
        "composerName": "Sam Smith, Calvin Harris, Jessie Reyez, Mikkel S. Eriksen, Tor Erik Hermansen, E.Y. \"Yip\" Harburg & Harold Arlen",
        "url": "https://music.apple.com/us/album/im-not-here-to-make-friends/1649325651?i=1649325667",
        "playParams": {
          "id": "1649325667",
          "kind": "song"
        },
        "discNumber": 1,
        "hasLyrics": true,
        "isAppleDigitalMaster": true,
        "name": "I'm Not Here To Make Friends",
        "previews": [
          {
            "url": "https://audio-ssl.itunes.apple.com/itunes-assets/AudioPreview126/v4/f8/b9/dc/f8b9dcee-26dc-a2b9-ecb9-7f30ed9a543e/mzaf_15443244977650399892.plus.aac.p.m4a"
          }
        ],
        "artistName": "Sam Smith"
      }
    },
    {
      "id": "1273710101",
      "type": "songs",
      "href": "/v1/catalog/us/songs/1273710101",
      "attributes": {
        "albumName": "Excitement of Youth",
        "genreNames": [
          "J-Pop",
          "Music"
        ],
        "trackNumber": 7,
        "releaseDate": "2017-04-14",
        "durationInMillis": 235241,
        "isrc": "JPWP01770243",
        "artwork": {
          "width": 1838,
          "height": 1600,
          "url": "https://is5-ssl.mzstatic.com/image/thumb/Music124/v4/d8/7b/7c/d87b7cfd-c88c-1003-bc5d-883882043e33/190295747138.jpg/{w}x{h}bb.jpg",
          "bgColor": "a4030f",
          "textColor1": "f5e5e7",
          "textColor2": "fe9792",
          "textColor3": "e5b8bb",
          "textColor4": "ec7a78"
        },
        "composerName": "Aimyon",
        "playParams": {
          "id": "1273710101",
          "kind": "song"
        },
        "url": "https://music.apple.com/us/album/ai-wo-tsutaetaidatoka/1273709789?i=1273710101",
        "discNumber": 1,
        "isAppleDigitalMaster": false,
        "hasLyrics": true,
        "name": "Ai Wo Tsutaetaidatoka",
        "previews": [
          {
            "url": "https://audio-ssl.itunes.apple.com/itunes-assets/AudioPreview115/v4/e4/94/3e/e4943e0b-6f14-f01e-29af-84344a082de2/mzaf_17657299734577883729.plus.aac.p.m4a"
          }
        ],
        "artistName": "Aimyon"
      }
    },
    {
      "id": "1670622074",
      "type": "songs",
      "href": "/v1/catalog/us/songs/1670622074",
      "attributes": {
        "albumName": "Teddy Bear - Single",
        "genreNames": [
          "K-Pop",
          "Music",
          "Pop"
        ],
        "trackNumber": 2,
        "releaseDate": "2023-02-03",
        "durationInMillis": 178293,
        "isrc": "KRA382300512",
        "artwork": {
          "width": 3000,
          "height": 3000,
          "url": "https://is5-ssl.mzstatic.com/image/thumb/Music116/v4/d3/e2/34/d3e23468-4920-f7b9-e955-322eb98af917/cover_KM0016800_1.jpg/{w}x{h}bb.jpg",
          "bgColor": "010101",
          "textColor1": "d458f5",
          "textColor2": "d522f6",
          "textColor3": "aa46c4",
          "textColor4": "ab1bc4"
        },
        "playParams": {
          "id": "1670622074",
          "kind": "song"
        },
        "url": "https://music.apple.com/us/album/poppy-korean-ver/1670622072?i=1670622074",
        "discNumber": 1,
        "isAppleDigitalMaster": false,
        "hasLyrics": true,
        "name": "Poppy (Korean Ver.)",
        "previews": [
          {
            "url": "https://audio-ssl.itunes.apple.com/itunes-assets/AudioPreview116/v4/df/89/14/df8914f4-b15f-fe49-1ed6-cc09128c7e1a/mzaf_11186161707499779216.plus.aac.p.m4a"
          }
        ],
        "artistName": "STAYC"
      }
    },
    {
      "id": "1670622073",
      "type": "songs",
      "href": "/v1/catalog/us/songs/1670622073",
      "attributes": {
        "albumName": "Teddy Bear - Single",
        "genreNames": [
          "K-Pop",
          "Music",
          "Pop"
        ],
        "trackNumber": 1,
        "releaseDate": "2023-02-14",
        "durationInMillis": 189773,
        "isrc": "KRA382300511",
        "artwork": {
          "width": 3000,
          "height": 3000,
          "url": "https://is5-ssl.mzstatic.com/image/thumb/Music116/v4/d3/e2/34/d3e23468-4920-f7b9-e955-322eb98af917/cover_KM0016800_1.jpg/{w}x{h}bb.jpg",
          "bgColor": "010101",
          "textColor1": "d458f5",
          "textColor2": "d522f6",
          "textColor3": "aa46c4",
          "textColor4": "ab1bc4"
        },
        "url": "https://music.apple.com/us/album/teddy-bear/1670622072?i=1670622073",
        "playParams": {
          "id": "1670622073",
          "kind": "song"
        },
        "discNumber": 1,
        "hasLyrics": true,
        "isAppleDigitalMaster": false,
        "name": "Teddy Bear",
        "previews": [
          {
            "url": "https://audio-ssl.itunes.apple.com/itunes-assets/AudioPreview116/v4/3d/df/90/3ddf9079-cd94-6c73-d437-1a1f2f28de15/mzaf_2025394688294119483.plus.aac.p.m4a"
          }
        ],
        "artistName": "STAYC"
      }
    },
    {
      "id": "1654124215",
      "type": "songs",
      "href": "/v1/catalog/us/songs/1654124215",
      "attributes": {
        "albumName": "Poppy - Single",
        "genreNames": [
          "K-Pop",
          "Music",
          "Pop"
        ],
        "trackNumber": 1,
        "releaseDate": "2022-11-16",
        "durationInMillis": 179867,
        "isrc": "JPPO02203955",
        "artwork": {
          "width": 3000,
          "height": 3000,
          "url": "https://is3-ssl.mzstatic.com/image/thumb/Music122/v4/5b/41/0b/5b410b11-0bfd-db80-2413-f2fd99454b5e/22UM1IM26561.rgb.jpg/{w}x{h}bb.jpg",
          "bgColor": "def5fd",
          "textColor1": "0c0a0a",
          "textColor2": "1a1a19",
          "textColor3": "36393b",
          "textColor4": "414546"
        },
        "composerName": "Rado, Fly-T & Will.B",
        "playParams": {
          "id": "1654124215",
          "kind": "song"
        },
        "url": "https://music.apple.com/us/album/poppy/1654124214?i=1654124215",
        "discNumber": 1,
        "isAppleDigitalMaster": false,
        "hasLyrics": false,
        "name": "Poppy",
        "previews": [
          {
            "url": "https://audio-ssl.itunes.apple.com/itunes-assets/AudioPreview122/v4/07/69/97/076997a3-8cab-d38b-edc7-8a642ef746da/mzaf_13303718278971176677.plus.aac.p.m4a"
          }
        ],
        "artistName": "STAYC"
      }
    },
    {
      "id": "1649467575",
      "type": "songs",
      "href": "/v1/catalog/us/songs/1649467575",
      "attributes": {
        "albumName": "ELEVEN -Japanese version- - Single",
        "genreNames": [
          "K-Pop",
          "Music",
          "Pop"
        ],
        "trackNumber": 2,
        "releaseDate": "2022-10-19",
        "durationInMillis": 145320,
        "isrc": "KRMIM2281382",
        "artwork": {
          "width": 3000,
          "height": 3000,
          "url": "https://is3-ssl.mzstatic.com/image/thumb/Music122/v4/b7/d7/18/b7d7185f-7b15-65db-9919-5282462f9863/4547366589269.jpg/{w}x{h}bb.jpg",
          "bgColor": "eab4d6",
          "textColor1": "0e0b04",
          "textColor2": "161616",
          "textColor3": "3a2d2e",
          "textColor4": "41363d"
        },
        "composerName": "Lauren Aquilina, Isaac Sakima & Joe Kearns",
        "url": "https://music.apple.com/us/album/queen-of-hearts/1649467561?i=1649467575",
        "playParams": {
          "id": "1649467575",
          "kind": "song"
        },
        "discNumber": 1,
        "hasLyrics": true,
        "isAppleDigitalMaster": false,
        "name": "Queen of Hearts",
        "previews": [
          {
            "url": "https://audio-ssl.itunes.apple.com/itunes-assets/AudioPreview122/v4/ee/7d/d2/ee7dd20a-824a-5e6a-dbd5-56f3090c83cc/mzaf_7769793116354059079.plus.aac.p.m4a"
          }
        ],
        "artistName": "IVE"
      }
    },
    {
      "id": "1435055380",
      "type": "songs",
      "href": "/v1/catalog/us/songs/1435055380",
      "attributes": {
        "albumName": "Lil' Touch - The 1st Single",
        "genreNames": [
          "K-Pop",
          "Music",
          "Pop"
        ],
        "trackNumber": 1,
        "releaseDate": "2018-09-05",
        "durationInMillis": 189846,
        "isrc": "KRA301800336",
        "artwork": {
          "width": 4000,
          "height": 4000,
          "url": "https://is2-ssl.mzstatic.com/image/thumb/Music114/v4/ff/30/91/ff309146-a4ac-d353-3699-842d790197cb/dj.gaxhueen.jpg/{w}x{h}bb.jpg",
          "bgColor": "010101",
          "textColor1": "fefefe",
          "textColor2": "dfdfdf",
          "textColor3": "cbcbcb",
          "textColor4": "b2b2b2"
        },
        "url": "https://music.apple.com/us/album/lil-touch/1435055371?i=1435055380",
        "playParams": {
          "id": "1435055380",
          "kind": "song"
        },
        "discNumber": 1,
        "hasLyrics": true,
        "isAppleDigitalMaster": false,
        "name": "Lil\u2019 Touch",
        "previews": [
          {
            "url": "https://audio-ssl.itunes.apple.com/itunes-assets/AudioPreview125/v4/e1/3e/06/e13e0676-d97a-5251-cdf0-61e6e712af3c/mzaf_10175526371952138997.plus.aac.p.m4a"
          }
        ],
        "artistName": "Girls' Generation-Oh!GG"
      }
    },
    {
      "id": "1445668827",
      "type": "songs",
      "href": "/v1/catalog/us/songs/1445668827",
      "attributes": {
        "albumName": "Louis Armstrong: Highlights from His Decca Years (The Original Decca Recordings)",
        "genreNames": [
          "Jazz",
          "Music"
        ],
        "trackNumber": 8,
        "releaseDate": "1950-06-26",
        "durationInMillis": 206333,
        "isrc": "USMC15076528",
        "artwork": {
          "width": 3000,
          "height": 3000,
          "url": "https://is2-ssl.mzstatic.com/image/thumb/Music122/v4/4e/94/ba/4e94ba92-463f-b37e-37d9-9f543b9700c4/06UMGIM03781.rgb.jpg/{w}x{h}bb.jpg",
          "bgColor": "e6632a",
          "textColor1": "110c0b",
          "textColor2": "23120e",
          "textColor3": "3b1d11",
          "textColor4": "4a2214"
        },
        "composerName": "Edith Piaf, Louis Guglielmi & Mack David",
        "url": "https://music.apple.com/us/album/la-vie-en-rose-single-version/1445668547?i=1445668827",
        "playParams": {
          "id": "1445668827",
          "kind": "song"
        },
        "discNumber": 2,
        "hasLyrics": false,
        "isAppleDigitalMaster": false,
        "name": "La vie en rose (Single Version)",
        "previews": [
          {
            "url": "https://audio-ssl.itunes.apple.com/itunes-assets/AudioPreview112/v4/8b/cf/c0/8bcfc04a-77b6-f0bf-f973-243c37060ea2/mzaf_17324403527218715526.plus.aac.p.m4a"
          }
        ],
        "artistName": "Louis Armstrong and His Orchestra"
      }
    },
    {
      "id": "1637490926",
      "type": "songs",
      "href": "/v1/catalog/us/songs/1637490926",
      "attributes": {
        "albumName": "Takin' It Back",
        "genreNames": [
          "Pop",
          "Music"
        ],
        "trackNumber": 2,
        "releaseDate": "2022-10-21",
        "durationInMillis": 134256,
        "isrc": "USSM12204574",
        "artwork": {
          "width": 3000,
          "height": 3000,
          "url": "https://is5-ssl.mzstatic.com/image/thumb/Music122/v4/55/dd/ab/55ddab67-26ec-e244-2c37-37f92b63bf19/196589366870.jpg/{w}x{h}bb.jpg",
          "bgColor": "cc003b",
          "textColor1": "f8f8f8",
          "textColor2": "b7dcf7",
          "textColor3": "efc6d2",
          "textColor4": "bbb0d2"
        },
        "composerName": "Meghan Trainor, Federico Vindver & Sean Douglas",
        "url": "https://music.apple.com/us/album/made-you-look/1637490577?i=1637490926",
        "playParams": {
          "id": "1637490926",
          "kind": "song"
        },
        "discNumber": 1,
        "hasLyrics": true,
        "isAppleDigitalMaster": false,
        "name": "Made You Look",
        "previews": [
          {
            "url": "https://audio-ssl.itunes.apple.com/itunes-assets/AudioPreview112/v4/3a/50/68/3a5068f1-f6a9-c8fc-0f23-ab8f8ce72f12/mzaf_319455285393302854.plus.aac.p.m4a"
          }
        ],
        "artistName": "Meghan Trainor"
      }
    },
    {
      "id": "1636642074",
      "type": "songs",
      "href": "/v1/catalog/us/songs/1636642074",
      "attributes": {
        "albumName": "SMARTPHONE - EP",
        "genreNames": [
          "K-Pop",
          "Music",
          "Pop"
        ],
        "trackNumber": 2,
        "releaseDate": "2022-08-03",
        "durationInMillis": 198587,
        "isrc": "KRMIM2242962",
        "artwork": {
          "width": 1400,
          "height": 1400,
          "url": "https://is5-ssl.mzstatic.com/image/thumb/Music112/v4/80/22/2e/80222eba-f219-310b-ed2f-8fff1db5492e/888272103687_Cover.jpg/{w}x{h}bb.jpg",
          "bgColor": "f0a3b5",
          "textColor1": "0e0b1d",
          "textColor2": "310c28",
          "textColor3": "3b293b",
          "textColor4": "572a44"
        },
        "composerName": "twlv, 72, Ollipop, Gavin Jones, Hayley Aitken & YENA",
        "url": "https://music.apple.com/us/album/smartphone/1636641846?i=1636642074",
        "playParams": {
          "id": "1636642074",
          "kind": "song"
        },
        "discNumber": 1,
        "hasLyrics": true,
        "isAppleDigitalMaster": false,
        "name": "SMARTPHONE",
        "previews": [
          {
            "url": "https://audio-ssl.itunes.apple.com/itunes-assets/AudioPreview112/v4/bc/b2/ba/bcb2ba3e-39fb-3b82-57a6-d5ea9bbd952c/mzaf_11876975758317856495.plus.aac.p.m4a"
          }
        ],
        "artistName": "YENA"
      }
    },
    {
      "id": "1578842459",
      "type": "songs",
      "href": "/v1/catalog/us/songs/1578842459",
      "attributes": {
        "albumName": "Play Game : Holiday - EP",
        "genreNames": [
          "K-Pop",
          "Music",
          "Pop"
        ],
        "trackNumber": 3,
        "releaseDate": "2021-08-04",
        "durationInMillis": 189307,
        "isrc": "KRA382159869",
        "artwork": {
          "width": 3000,
          "height": 3000,
          "url": "https://is2-ssl.mzstatic.com/image/thumb/Music125/v4/fe/ff/76/feff7621-ce3c-0bbf-57bc-5c8fe72994da/1.jpg/{w}x{h}bb.jpg",
          "bgColor": "fdf7fb",
          "textColor1": "030d05",
          "textColor2": "203819",
          "textColor3": "353c36",
          "textColor4": "4c5e46"
        },
        "playParams": {
          "id": "1578842459",
          "kind": "song"
        },
        "url": "https://music.apple.com/us/album/holiday-party/1578842456?i=1578842459",
        "discNumber": 1,
        "isAppleDigitalMaster": false,
        "hasLyrics": true,
        "name": "Holiday Party",
        "previews": [
          {
            "url": "https://audio-ssl.itunes.apple.com/itunes-assets/AudioPreview122/v4/2e/36/81/2e3681f0-2c75-af46-9823-d5232b68799b/mzaf_6475404558975475914.plus.aac.p.m4a"
          }
        ],
        "artistName": "Weeekly"
      }
    },
    {
      "id": "1558430430",
      "type": "songs",
      "href": "/v1/catalog/us/songs/1558430430",
      "attributes": {
        "albumName": "We Play - EP",
        "genreNames": [
          "K-Pop",
          "Music",
          "Pop"
        ],
        "trackNumber": 1,
        "releaseDate": "2021-03-17",
        "durationInMillis": 183387,
        "isrc": "KRA382101557",
        "artwork": {
          "width": 3000,
          "height": 3000,
          "url": "https://is1-ssl.mzstatic.com/image/thumb/Music125/v4/24/13/9a/24139afb-ce83-1828-ff8c-7d626bf30085/cover.jpg/{w}x{h}bb.jpg",
          "bgColor": "0096d6",
          "textColor1": "050104",
          "textColor2": "291610",
          "textColor3": "041f2e",
          "textColor4": "213037"
        },
        "url": "https://music.apple.com/us/album/yummy/1558430429?i=1558430430",
        "playParams": {
          "id": "1558430430",
          "kind": "song"
        },
        "discNumber": 1,
        "hasLyrics": true,
        "isAppleDigitalMaster": false,
        "name": "Yummy!",
        "previews": [
          {
            "url": "https://audio-ssl.itunes.apple.com/itunes-assets/AudioPreview122/v4/98/ac/e8/98ace8d7-8e21-f144-9361-183f5570d85a/mzaf_4931385076602960967.plus.aac.p.m4a"
          }
        ],
        "artistName": "Weeekly"
      }
    },
    {
      "id": "1621089856",
      "type": "songs",
      "href": "/v1/catalog/us/songs/1621089856",
      "attributes": {
        "albumName": "Fearless - EP",
        "genreNames": [
          "K-Pop",
          "Music",
          "Pop"
        ],
        "trackNumber": 5,
        "releaseDate": "2022-05-02",
        "durationInMillis": 196540,
        "isrc": "USA2P2219221",
        "artwork": {
          "width": 1400,
          "height": 1400,
          "url": "https://is3-ssl.mzstatic.com/image/thumb/Music116/v4/90/dc/9f/90dc9fdb-c0f3-f506-0942-0e33c94d26f4/196922016622_Cover.jpg/{w}x{h}bb.jpg",
          "bgColor": "000000",
          "textColor1": "ffffff",
          "textColor2": "dedede",
          "textColor3": "cbcbcb",
          "textColor4": "b1b1b1"
        },
        "composerName": "SCORE(13), MEGATONE(13), Danke, ABIR, Kayofkaj, Nermin Harambasic (Dsign Music), Lady V, \uae40\uc778\ud615 & Sunshine (Cazzi Opeia & Ellen Berg)",
        "playParams": {
          "id": "1621089856",
          "kind": "song"
        },
        "url": "https://music.apple.com/us/album/sour-grapes/1621089349?i=1621089856",
        "discNumber": 1,
        "isAppleDigitalMaster": false,
        "hasLyrics": true,
        "name": "Sour Grapes",
        "previews": [
          {
            "url": "https://audio-ssl.itunes.apple.com/itunes-assets/AudioPreview122/v4/7f/60/fb/7f60fb74-1af7-9276-12f3-a55dccbbccec/mzaf_11191739939816791003.plus.aac.p.m4a"
          }
        ],
        "artistName": "LE SSERAFIM"
      }
    },
    {
      "id": "1621089614",
      "type": "songs",
      "href": "/v1/catalog/us/songs/1621089614",
      "attributes": {
        "albumName": "Fearless - EP",
        "genreNames": [
          "K-Pop",
          "Music",
          "Pop"
        ],
        "trackNumber": 3,
        "releaseDate": "2022-05-02",
        "durationInMillis": 201895,
        "isrc": "USA2P2219220",
        "artwork": {
          "width": 1400,
          "height": 1400,
          "url": "https://is3-ssl.mzstatic.com/image/thumb/Music116/v4/90/dc/9f/90dc9fdb-c0f3-f506-0942-0e33c94d26f4/196922016622_Cover.jpg/{w}x{h}bb.jpg",
          "bgColor": "000000",
          "textColor1": "ffffff",
          "textColor2": "dedede",
          "textColor3": "cbcbcb",
          "textColor4": "b1b1b1"
        },
        "composerName": "SCORE(13), MEGATONE(13), Jonna Hall, \uac00\uc601(PNP), \uae40\uc778\ud615, Danke, \uae40\ucc44\uc6d0, Ronnie Icon, Caroline Gustavsson & \ud5c8\uc724\uc9c4",
        "url": "https://music.apple.com/us/album/blue-flame/1621089349?i=1621089614",
        "playParams": {
          "id": "1621089614",
          "kind": "song"
        },
        "discNumber": 1,
        "hasLyrics": true,
        "isAppleDigitalMaster": false,
        "name": "Blue Flame",
        "previews": [
          {
            "url": "https://audio-ssl.itunes.apple.com/itunes-assets/AudioPreview116/v4/06/6e/8e/066e8ee8-22a5-29ce-9840-455cfa9e7f2f/mzaf_10761610533428846279.plus.aac.p.m4a"
          }
        ],
        "artistName": "LE SSERAFIM"
      }
    },
    {
      "id": "1647830394",
      "type": "songs",
      "href": "/v1/catalog/us/songs/1647830394",
      "attributes": {
        "albumName": "ANTIFRAGILE - EP",
        "genreNames": [
          "K-Pop",
          "Music",
          "Pop"
        ],
        "trackNumber": 3,
        "releaseDate": "2022-10-17",
        "durationInMillis": 196365,
        "isrc": "USA2P2230330",
        "artwork": {
          "width": 1400,
          "height": 1400,
          "url": "https://is4-ssl.mzstatic.com/image/thumb/Music122/v4/51/43/f4/5143f45c-bf3c-b880-8564-bc9bac7e535c/192641874413_Cover.jpg/{w}x{h}bb.jpg",
          "bgColor": "ffffff",
          "textColor1": "000000",
          "textColor2": "212121",
          "textColor3": "333333",
          "textColor4": "4e4e4e"
        },
        "composerName": "\uc774\ud615\uc11d(PNP), SCORE(13), Nikolay Mohr, \ubc15\uc0c1\uc720(PNP), \uc870\uc724\uacbd, Hayes Kramer, BLVSH, Jaro, Charli Taft, \uae40\ucc44\uc544(153/Joombas), Maggie Szabo, \"Hitman\" Bang, \ud5c8\uc724\uc9c4, Daniel \"Obi\" Klein, MEGATONE(13), Jonna Hall & Danke",
        "playParams": {
          "id": "1647830394",
          "kind": "song"
        },
        "url": "https://music.apple.com/us/album/impurities/1647830231?i=1647830394",
        "discNumber": 1,
        "isAppleDigitalMaster": false,
        "hasLyrics": true,
        "name": "Impurities",
        "previews": [
          {
            "url": "https://audio-ssl.itunes.apple.com/itunes-assets/AudioPreview122/v4/9b/63/aa/9b63aaae-cc83-39ec-0a06-a564861f4f11/mzaf_15166524560809953058.plus.aac.p.m4a"
          }
        ],
        "artistName": "LE SSERAFIM"
      }
    },
    {
      "id": "1670255969",
      "type": "songs",
      "href": "/v1/catalog/us/songs/1670255969",
      "attributes": {
        "albumName": "Bye My Blue - EP",
        "genreNames": [
          "R&B/Soul",
          "Music"
        ],
        "trackNumber": 1,
        "releaseDate": "2023-02-12",
        "durationInMillis": 190587,
        "isrc": "KRMIM2331183",
        "artwork": {
          "width": 2400,
          "height": 2400,
          "url": "https://is3-ssl.mzstatic.com/image/thumb/Music116/v4/9a/2d/cf/9a2dcf6d-0d2d-1fd1-c614-87b28d3c41e7/5054197557101.jpg/{w}x{h}bb.jpg",
          "bgColor": "a2a6b1",
          "textColor1": "080503",
          "textColor2": "090603",
          "textColor3": "272526",
          "textColor4": "282626"
        },
        "composerName": "Dept, Roydo, Clam, Sunkiss & Suru",
        "url": "https://music.apple.com/us/album/broken-feat-j-o-y-suru/1670255968?i=1670255969",
        "playParams": {
          "id": "1670255969",
          "kind": "song"
        },
        "discNumber": 1,
        "hasLyrics": true,
        "isAppleDigitalMaster": false,
        "name": "Broken (feat. J.O.Y & suru)",
        "previews": [
          {
            "url": "https://audio-ssl.itunes.apple.com/itunes-assets/AudioPreview126/v4/fe/df/87/fedf8796-9f58-69b9-805c-5f27cf9ad70b/mzaf_12613675243245092065.plus.aac.p.m4a"
          }
        ],
        "artistName": "Dept"
      }
    },
    {
      "id": "1670051176",
      "type": "songs",
      "href": "/v1/catalog/us/songs/1670051176",
      "attributes": {
        "albumName": "Killer: The 2nd Album Repackage",
        "genreNames": [
          "K-Pop",
          "Music",
          "Pop"
        ],
        "trackNumber": 1,
        "releaseDate": "2023-02-13",
        "durationInMillis": 230733,
        "isrc": "KRA302300029",
        "artwork": {
          "width": 4000,
          "height": 4000,
          "url": "https://is4-ssl.mzstatic.com/image/thumb/Music126/v4/0c/b5/cb/0cb5cb34-a6b4-dc25-5da7-6074237b1aec/KEY_Digital_Cover.jpg/{w}x{h}bb.jpg",
          "bgColor": "000000",
          "textColor1": "f0f2f6",
          "textColor2": "fbc8de",
          "textColor3": "c0c1c5",
          "textColor4": "c9a0b2"
        },
        "composerName": "Christoph Cronauer, Simon Klose, Rita Bavanati & Thilo Berndt",
        "playParams": {
          "id": "1670051176",
          "kind": "song"
        },
        "url": "https://music.apple.com/us/album/killer/1670050845?i=1670051176",
        "discNumber": 1,
        "isAppleDigitalMaster": false,
        "hasLyrics": true,
        "name": "Killer",
        "previews": [
          {
            "url": "https://audio-ssl.itunes.apple.com/itunes-assets/AudioPreview116/v4/96/9d/78/969d78f0-eed1-20c5-dd3c-d02e19e57461/mzaf_2475226049334755213.plus.aac.p.m4a"
          }
        ],
        "artistName": "KEY"
      }
    },
    {
      "id": "1594292084",
      "type": "songs",
      "href": "/v1/catalog/us/songs/1594292084",
      "attributes": {
        "albumName": "YOUNHA 6th Album 'END THEORY'",
        "genreNames": [
          "K-Pop",
          "Music",
          "Pop",
          "Rock"
        ],
        "trackNumber": 3,
        "releaseDate": "2021-11-16",
        "durationInMillis": 206627,
        "isrc": "KRA382163578",
        "artwork": {
          "width": 3000,
          "height": 3000,
          "url": "https://is2-ssl.mzstatic.com/image/thumb/Music126/v4/f7/ec/83/f7ec837e-3a7f-6476-1890-be94cbbc887b/YOUNHA_6th_Album_END_THEORY_Digitalcover.jpg/{w}x{h}bb.jpg",
          "bgColor": "fff9d9",
          "textColor1": "0b0202",
          "textColor2": "4b1e10",
          "textColor3": "3c332d",
          "textColor4": "6f4a38"
        },
        "playParams": {
          "id": "1594292084",
          "kind": "song"
        },
        "url": "https://music.apple.com/us/album/oort-cloud/1594292081?i=1594292084",
        "discNumber": 1,
        "isAppleDigitalMaster": false,
        "hasLyrics": true,
        "name": "Oort Cloud",
        "previews": [
          {
            "url": "https://audio-ssl.itunes.apple.com/itunes-assets/AudioPreview126/v4/19/ce/79/19ce7920-99b9-358a-190d-b7b748d4de02/mzaf_13520814028107338416.plus.aac.p.m4a"
          }
        ],
        "artistName": "Younha"
      }
    },
    {
      "id": "1440715697",
      "type": "songs",
      "href": "/v1/catalog/us/songs/1440715697",
      "attributes": {
        "albumName": "The Visitors (Deluxe Edition)",
        "genreNames": [
          "Pop",
          "Music",
          "Britpop",
          "Soft Rock",
          "Alternative",
          "New Wave",
          "Worldwide",
          "Europe",
          "Pop/Rock"
        ],
        "trackNumber": 8,
        "releaseDate": "1981-06-01",
        "durationInMillis": 233720,
        "isrc": "SEAYD8102080",
        "artwork": {
          "width": 3000,
          "height": 3000,
          "url": "https://is2-ssl.mzstatic.com/image/thumb/Music124/v4/e0/9b/13/e09b134a-0de4-f95d-d751-cf10cea4f343/12UMGIM11986.rgb.jpg/{w}x{h}bb.jpg",
          "bgColor": "5d271b",
          "textColor1": "ffe8e7",
          "textColor2": "f5e3dc",
          "textColor3": "dec1be",
          "textColor4": "d7bdb5"
        },
        "composerName": "Bj\u00f6rn Ulvaeus & Benny Andersson",
        "url": "https://music.apple.com/us/album/slipping-through-my-fingers/1440715246?i=1440715697",
        "playParams": {
          "id": "1440715697",
          "kind": "song"
        },
        "discNumber": 1,
        "hasLyrics": true,
        "isAppleDigitalMaster": false,
        "name": "Slipping Through My Fingers",
        "previews": [
          {
            "url": "https://audio-ssl.itunes.apple.com/itunes-assets/AudioPreview125/v4/b2/83/7f/b2837f5b-cd8f-d0b7-8811-ddf830909d8b/mzaf_1014457160493636232.plus.aac.p.m4a"
          }
        ],
        "artistName": "ABBA"
      }
    },
    {
      "id": "1661231084",
      "type": "songs",
      "href": "/v1/catalog/us/songs/1661231084",
      "attributes": {
        "albumName": "Mantrum - Single",
        "genreNames": [
          "Pop",
          "Music"
        ],
        "trackNumber": 1,
        "releaseDate": "2023-01-18",
        "durationInMillis": 154814,
        "isrc": "US39N2205469",
        "artwork": {
          "width": 3000,
          "height": 3000,
          "url": "https://is3-ssl.mzstatic.com/image/thumb/Music113/v4/ef/b8/87/efb88730-5398-34ed-11f7-e5052956c1cd/197338937242.jpg/{w}x{h}bb.jpg",
          "bgColor": "470002",
          "textColor1": "eeeeee",
          "textColor2": "eeb6b8",
          "textColor3": "ccbebf",
          "textColor4": "cd9194"
        },
        "composerName": "Barry Cohen, Colin Magalong, Elana Caceres, Lillian Gillespie, Makhyli Simpson, Olivia Ruby & Queenie Mae Villaluz",
        "playParams": {
          "id": "1661231084",
          "kind": "song"
        },
        "url": "https://music.apple.com/us/album/mantrum/1661231082?i=1661231084",
        "discNumber": 1,
        "isAppleDigitalMaster": false,
        "hasLyrics": true,
        "name": "Mantrum",
        "previews": [
          {
            "url": "https://audio-ssl.itunes.apple.com/itunes-assets/AudioPreview123/v4/64/78/0c/64780cd6-bd05-830b-2af0-537c305c8ba5/mzaf_8725942745776842741.plus.aac.p.m4a"
          }
        ],
        "artistName": "Boys World"
      }
    },
    {
      "id": "1672473320",
      "type": "songs",
      "href": "/v1/catalog/us/songs/1672473320",
      "attributes": {
        "albumName": "ABYSS - Single",
        "genreNames": [
          "K-Pop",
          "Music",
          "Pop",
          "Rock"
        ],
        "trackNumber": 1,
        "releaseDate": "2023-02-22",
        "durationInMillis": 232040,
        "isrc": "KRA382300896",
        "artwork": {
          "width": 3000,
          "height": 3000,
          "url": "https://is5-ssl.mzstatic.com/image/thumb/Music126/v4/ec/8c/b0/ec8cb0dd-e219-731f-bdfe-be0460d3d6f3/cover_KM0016894_1.jpg/{w}x{h}bb.jpg",
          "bgColor": "ffffff",
          "textColor1": "0d0d0d",
          "textColor2": "212121",
          "textColor3": "3d3d3d",
          "textColor4": "4e4e4e"
        },
        "url": "https://music.apple.com/us/album/abyss/1672473319?i=1672473320",
        "playParams": {
          "id": "1672473320",
          "kind": "song"
        },
        "discNumber": 1,
        "hasLyrics": true,
        "isAppleDigitalMaster": false,
        "name": "ABYSS",
        "previews": [
          {
            "url": "https://audio-ssl.itunes.apple.com/itunes-assets/AudioPreview126/v4/67/d1/00/67d10033-cd8a-4aa3-bad1-3b67f4e305b4/mzaf_4317020986143505565.plus.aac.p.m4a"
          }
        ],
        "artistName": "WOODZ"
      }
    },
    {
      "id": "1660564714",
      "type": "songs",
      "href": "/v1/catalog/us/songs/1660564714",
      "attributes": {
        "albumName": "The Present - Single",
        "genreNames": [
          "K-Pop",
          "Music",
          "Pop",
          "R&B/Soul"
        ],
        "trackNumber": 2,
        "releaseDate": "2022-12-22",
        "durationInMillis": 168573,
        "isrc": "KRA382209101",
        "artwork": {
          "width": 3000,
          "height": 3000,
          "url": "https://is2-ssl.mzstatic.com/image/thumb/Music112/v4/cc/99/c3/cc99c3d0-3bb7-d34d-33a6-806c1f76c5a2/cover_KM0016648_1.jpg/{w}x{h}bb.jpg",
          "bgColor": "d9d4db",
          "textColor1": "161617",
          "textColor2": "530a13",
          "textColor3": "3d3c3e",
          "textColor4": "6e323b"
        },
        "url": "https://music.apple.com/us/album/chemistry/1660564708?i=1660564714",
        "playParams": {
          "id": "1660564714",
          "kind": "song"
        },
        "discNumber": 1,
        "hasLyrics": true,
        "isAppleDigitalMaster": false,
        "name": "CHEMISTRY",
        "previews": [
          {
            "url": "https://audio-ssl.itunes.apple.com/itunes-assets/AudioPreview122/v4/52/65/97/5265972f-625f-7943-9f4f-bf73dbacdf6c/mzaf_7702705794990389848.plus.aac.p.m4a"
          }
        ],
        "artistName": "Moon Byul"
      }
    },
    {
      "id": "1670052592",
      "type": "songs",
      "href": "/v1/catalog/us/songs/1670052592",
      "attributes": {
        "albumName": "In other season - Single",
        "genreNames": [
          "Folk",
          "Music",
          "Pop",
          "K-Pop"
        ],
        "trackNumber": 1,
        "releaseDate": "2023-02-07",
        "durationInMillis": 244809,
        "isrc": "KRMIM2317578",
        "artwork": {
          "width": 3000,
          "height": 3000,
          "url": "https://is4-ssl.mzstatic.com/image/thumb/Music126/v4/43/19/45/431945b4-7539-6b3f-2b6e-5f0ea3ca7b4e/191953261966.jpg/{w}x{h}bb.jpg",
          "bgColor": "151611",
          "textColor1": "f6f2f3",
          "textColor2": "e3dac4",
          "textColor3": "c9c6c6",
          "textColor4": "b9b3a0"
        },
        "composerName": "SUNGHWI",
        "playParams": {
          "id": "1670052592",
          "kind": "song"
        },
        "url": "https://music.apple.com/us/album/in-other-season/1670052591?i=1670052592",
        "discNumber": 1,
        "isAppleDigitalMaster": false,
        "hasLyrics": true,
        "name": "In other season",
        "previews": [
          {
            "url": "https://audio-ssl.itunes.apple.com/itunes-assets/AudioPreview116/v4/f3/53/7e/f3537e1e-85ea-12c8-4f05-3cbdf1a0c1e6/mzaf_1376378571333433548.plus.aac.p.m4a"
          }
        ],
        "artistName": "SUNGHWI"
      }
    },
    {
      "id": "1668065142",
      "type": "songs",
      "href": "/v1/catalog/us/songs/1668065142",
      "attributes": {
        "albumName": "Umm (With Park Jun) - Single",
        "genreNames": [
          "K-Pop",
          "Music",
          "Pop"
        ],
        "trackNumber": 1,
        "releaseDate": "2023-01-27",
        "durationInMillis": 218901,
        "isrc": "KRF452300003",
        "artwork": {
          "width": 3000,
          "height": 3000,
          "url": "https://is4-ssl.mzstatic.com/image/thumb/Music113/v4/fd/a9/39/fda939a6-fe64-d5c1-70b1-23a6575bf01a/191953259277.jpg/{w}x{h}bb.jpg",
          "bgColor": "1a201e",
          "textColor1": "d3c5b8",
          "textColor2": "d8bcaa",
          "textColor3": "aea499",
          "textColor4": "b29c8e"
        },
        "composerName": "ShortPaper, \ud55c\uc131\ud76c & wudstak",
        "playParams": {
          "id": "1668065142",
          "kind": "song"
        },
        "url": "https://music.apple.com/us/album/umm-with-park-jun/1668065141?i=1668065142",
        "discNumber": 1,
        "isAppleDigitalMaster": false,
        "hasLyrics": true,
        "name": "Umm (With Park Jun)",
        "previews": [
          {
            "url": "https://audio-ssl.itunes.apple.com/itunes-assets/AudioPreview123/v4/fd/07/01/fd070133-f7f1-4fab-fdc2-46cfab1588f8/mzaf_3739249546691681839.plus.aac.p.m4a"
          }
        ],
        "artistName": "ShortPaper"
      }
    },
    {
      "id": "1639416903",
      "type": "songs",
      "href": "/v1/catalog/us/songs/1639416903",
      "attributes": {
        "albumName": "After LIKE - Single",
        "genreNames": [
          "K-Pop",
          "Music",
          "Pop"
        ],
        "trackNumber": 1,
        "releaseDate": "2022-08-22",
        "durationInMillis": 176973,
        "isrc": "QMBZ92254957",
        "artwork": {
          "width": 3000,
          "height": 3000,
          "url": "https://is2-ssl.mzstatic.com/image/thumb/Music122/v4/01/f5/0a/01f50af1-89da-cb51-a809-c613600451e9/196925429900.jpg/{w}x{h}bb.jpg",
          "bgColor": "00ff00",
          "textColor1": "000000",
          "textColor2": "002f00",
          "textColor3": "003300",
          "textColor4": "005800"
        },
        "composerName": "Ji Eum Seo, RYAN JHUN, Anders Nilsen, Andre Jensen, Iselin Solheim, F. Perren & D Fekaris",
        "url": "https://music.apple.com/us/album/after-like/1639416895?i=1639416903",
        "playParams": {
          "id": "1639416903",
          "kind": "song"
        },
        "discNumber": 1,
        "hasLyrics": true,
        "isAppleDigitalMaster": false,
        "name": "After LIKE",
        "previews": [
          {
            "url": "https://audio-ssl.itunes.apple.com/itunes-assets/AudioPreview112/v4/c1/6d/89/c16d89c2-2c5a-2af1-c7ab-795a43da6799/mzaf_12151411481091015950.plus.aac.p.m4a"
          }
        ],
        "artistName": "IVE"
      }
    },
    {
      "id": "1657231962",
      "type": "songs",
      "href": "/v1/catalog/us/songs/1657231962",
      "attributes": {
        "albumName": "Ditto - Single",
        "genreNames": [
          "K-Pop",
          "Music",
          "Pop"
        ],
        "trackNumber": 1,
        "releaseDate": "2022-12-19",
        "durationInMillis": 185507,
        "isrc": "USA2P2254487",
        "artwork": {
          "width": 1400,
          "height": 1400,
          "url": "https://is4-ssl.mzstatic.com/image/thumb/Music112/v4/f6/29/42/f629426e-92fe-535c-cbe4-76e70850819b/196922287107_Cover.jpg/{w}x{h}bb.jpg",
          "bgColor": "fdfcff",
          "textColor1": "36080e",
          "textColor2": "440a11",
          "textColor3": "5e393e",
          "textColor4": "693b41"
        },
        "composerName": "Ylva Dimberg, 250, Hyu-il Cho (The Black Skirts), Oohyo & MINJI",
        "url": "https://music.apple.com/us/album/ditto/1657231957?i=1657231962",
        "playParams": {
          "id": "1657231962",
          "kind": "song"
        },
        "discNumber": 1,
        "hasLyrics": true,
        "isAppleDigitalMaster": false,
        "name": "Ditto",
        "previews": [
          {
            "url": "https://audio-ssl.itunes.apple.com/itunes-assets/AudioPreview122/v4/67/af/3d/67af3de7-8967-bc14-073d-a8712338ac32/mzaf_190692881480987912.plus.aac.p.m4a"
          }
        ],
        "artistName": "NewJeans"
      }
    },
    {
      "id": "1654019898",
      "type": "songs",
      "href": "/v1/catalog/us/songs/1654019898",
      "attributes": {
        "albumName": "CHESHIRE - EP",
        "genreNames": [
          "Pop",
          "Music"
        ],
        "trackNumber": 1,
        "releaseDate": "2022-11-30",
        "durationInMillis": 182453,
        "isrc": "US5TA2200143",
        "artwork": {
          "width": 1400,
          "height": 1400,
          "url": "https://is2-ssl.mzstatic.com/image/thumb/Music122/v4/e8/aa/52/e8aa52be-338e-0903-fb66-cc8de1f37dcc/738676860368_Cover.jpg/{w}x{h}bb.jpg",
          "bgColor": "eee7ee",
          "textColor1": "010d0f",
          "textColor2": "372f2d",
          "textColor3": "30393c",
          "textColor4": "5c5454"
        },
        "composerName": "Tim Tan, Ciara Muscat, Josefin Glenmark, Jar, Justin Reinstein, JJean, Hwang Sumin & Jeong Hari",
        "playParams": {
          "id": "1654019898",
          "kind": "song"
        },
        "url": "https://music.apple.com/us/album/cheshire/1654019775?i=1654019898",
        "discNumber": 1,
        "isAppleDigitalMaster": false,
        "hasLyrics": true,
        "name": "Cheshire",
        "previews": [
          {
            "url": "https://audio-ssl.itunes.apple.com/itunes-assets/AudioPreview112/v4/10/65/1a/10651a53-f512-ed86-e483-2e08b6960fc0/mzaf_16828220535679436785.plus.aac.p.m4a"
          }
        ],
        "artistName": "ITZY",
        "editorialNotes": {
          "standard": "K-pop\u2019s fab five pack their dance bops with mystery and mischief.",
          "short": "K-pop\u2019s fab five pack their dance bops with mystery and mischief."
        }
      }
    },
    {
      "id": "1611486063",
      "type": "songs",
      "href": "/v1/catalog/us/songs/1611486063",
      "attributes": {
        "albumName": "Search: WWW (Original Television Soundtrack)",
        "genreNames": [
          "Soundtrack",
          "Music"
        ],
        "trackNumber": 1,
        "releaseDate": "2019-06-07",
        "durationInMillis": 204000,
        "isrc": "KRA491900393",
        "artwork": {
          "width": 1400,
          "height": 1400,
          "url": "https://is4-ssl.mzstatic.com/image/thumb/Music126/v4/f2/45/16/f245166b-05a8-1ba0-7ec8-ba466f8c5e50/8809658314871_Cover.jpg/{w}x{h}bb.jpg",
          "bgColor": "fff3c9",
          "textColor1": "060404",
          "textColor2": "1b2246",
          "textColor3": "38342b",
          "textColor4": "484b60"
        },
        "composerName": "Kako & CURTIS F",
        "url": "https://music.apple.com/us/album/milky-way-between-us/1611486062?i=1611486063",
        "playParams": {
          "id": "1611486063",
          "kind": "song"
        },
        "discNumber": 1,
        "hasLyrics": true,
        "isAppleDigitalMaster": false,
        "name": "Milky Way Between Us",
        "previews": [
          {
            "url": "https://audio-ssl.itunes.apple.com/itunes-assets/AudioPreview126/v4/48/17/0c/48170c17-8830-2aba-1e1b-33570b55476c/mzaf_10920056340067788709.plus.aac.p.m4a"
          }
        ],
        "artistName": "O3ohn"
      }
    },
    {
      "id": "1635469851",
      "type": "songs",
      "href": "/v1/catalog/us/songs/1635469851",
      "attributes": {
        "albumName": "NewJeans 1st EP 'New Jeans'",
        "genreNames": [
          "K-Pop",
          "Music",
          "Pop"
        ],
        "trackNumber": 2,
        "releaseDate": "2022-08-01",
        "durationInMillis": 179027,
        "isrc": "USA2P2230222",
        "artwork": {
          "width": 1400,
          "height": 1400,
          "url": "https://is3-ssl.mzstatic.com/image/thumb/Music112/v4/4e/64/34/4e64344b-3ac6-c503-2c41-257a15401416/192641873096_Cover.jpg/{w}x{h}bb.jpg",
          "bgColor": "fbfffc",
          "textColor1": "111431",
          "textColor2": "13172c",
          "textColor3": "3f435a",
          "textColor4": "424556"
        },
        "composerName": "Ylva Dimberg, 250, Gigi & Hanni",
        "playParams": {
          "id": "1635469851",
          "kind": "song"
        },
        "url": "https://music.apple.com/us/album/hype-boy/1635469682?i=1635469851",
        "discNumber": 1,
        "isAppleDigitalMaster": false,
        "hasLyrics": true,
        "name": "Hype Boy",
        "previews": [
          {
            "url": "https://audio-ssl.itunes.apple.com/itunes-assets/AudioPreview112/v4/43/cc/b8/43ccb8f7-fc0a-2a2f-c119-472f602773b4/mzaf_17285312710782684304.plus.aac.p.m4a"
          }
        ],
        "artistName": "NewJeans"
      }
    }
  ]
}